hondana/__init__.py
hondana/__main__.py
hondana/artist.py
hondana/author.py
hondana/chapter.py
hondana/client.py
hondana/collections.py
hondana/cover.py
hondana/custom_list.py
hondana/enums.py
hondana/errors.py
hondana/forums.py
hondana/http.py
hondana/legacy.py
hondana/manga.py
hondana/py.typed
hondana/query.py
hondana/relationship.py
hondana/report.py
hondana/scanlator_group.py
hondana/tags.py
hondana/user.py
hondana/utils.py
hondana/extras/report_reasons.json
hondana/extras/tags.json
hondana/types_/account.py
hondana/types_/artist.py
hondana/types_/auth.py
hondana/types_/author.py
hondana/types_/chapter.py
hondana/types_/common.py
hondana/types_/cover.py
hondana/types_/custom_list.py
hondana/types_/errors.py
hondana/types_/forums.py
hondana/types_/legacy.py
hondana/types_/manga.py
hondana/types_/relationship.py
hondana/types_/report.py
hondana/types_/scanlator_group.py
hondana/types_/settings.py
hondana/types_/statistics.py
hondana/types_/tags.py
hondana/types_/token.py
hondana/types_/upload.py
hondana/types_/user.py
hondana-3.7.5.dist-info/METADATA
hondana-3.7.5.dist-info/WHEEL
hondana-3.7.5.dist-info/entry_points.txt
hondana-3.7.5.dist-info/licenses/LICENSE
hondana-3.7.5.dist-info/RECORD
