Metadata-Version: 2.4
Name: hondana
Version: 3.7.5
Summary: An asynchronous wrapper around the MangaDex v5 API
Project-URL: Issue Tracker, https://github.com/AbstractUmbra/hondana/issues
Project-URL: Discord, https://discord.gg/aYGYJxwqe5
Project-URL: Repository, https://github.com/AbstractUmbra/hondana
Author-email: Alex Nørgaard <umbra@abstractumbra.dev>
License: Copyright 2021-Present AbstractUmbra
License-File: LICENSE
Keywords: api,manga,mangadex,wrapper
Classifier: Intended Audience :: Developers
Classifier: License :: OSI Approved :: MIT License
Classifier: Natural Language :: English
Classifier: Operating System :: OS Independent
Classifier: Programming Language :: Python :: 3.11
Classifier: Programming Language :: Python :: 3.12
Classifier: Topic :: Internet
Classifier: Typing :: Typed
Requires-Python: <4.0,>=3.11
Requires-Dist: aiohttp<4.0,>=3.9
Provides-Extra: speed
Requires-Dist: aiohttp[speedups]; extra == 'speed'
Requires-Dist: orjson; extra == 'speed'
